tmidi.py
circuitpython_tmidi-2.0.0.dist-info/licenses/LICENSE
circuitpython_tmidi-2.0.0.dist-info/METADATA
circuitpython_tmidi-2.0.0.dist-info/WHEEL
circuitpython_tmidi-2.0.0.dist-info/top_level.txt
circuitpython_tmidi-2.0.0.dist-info/RECORD
