Metadata-Version: 2.4
Name: circuitpython-tmidi
Version: 2.0.0
Summary: MIDI library for CircuitPython
Author-email: Tod Kurt <tod@todbot.com>
License: MIT
Project-URL: Homepage, https://github.com/todbot/CircuitPython_TMIDI
Keywords: adafruit,blinka,circuitpython,micropython,tmidi,midi
Classifier: Intended Audience :: Developers
Classifier: Topic :: Software Development :: Libraries
Classifier: Topic :: Software Development :: Embedded Systems
Classifier: Topic :: System :: Hardware
Classifier: License :: OSI Approved :: MIT License
Classifier: Programming Language :: Python :: 3
License-File: LICENSE
Requires-Dist: Adafruit-Blinka
Provides-Extra: optional
Dynamic: license-file
